README.md
setup.cfg
setup.py
tonyc_utils/__init__.py
tonyc_utils/logging.py
tonyc_utils/prompts.py
tonyc_utils.egg-info/PKG-INFO
tonyc_utils.egg-info/SOURCES.txt
tonyc_utils.egg-info/dependency_links.txt
tonyc_utils.egg-info/top_level.txt