Metadata-Version: 1.1
Name: tonyc-utils
Version: 1.0.1
Summary: Various utilities -- most notably logging helpers
Home-page: UNKNOWN
Author: Tony Cebzanov
Author-email: tonycpsu@gmail.com
License: UNKNOWN
Platform: UNKNOWN
Classifier: Environment :: Console
Classifier: Intended Audience :: Developers
